prs_utility/__init__.py
prs_utility/core.py
prs_utility/util.py
prs_utility-0.0.8.dist-info/LICENSE
prs_utility-0.0.8.dist-info/METADATA
prs_utility-0.0.8.dist-info/WHEEL
prs_utility-0.0.8.dist-info/top_level.txt
prs_utility-0.0.8.dist-info/RECORD
